statcamp/__init__.py
statcamp/base.py
statcamp-0.0.2.dist-info/DESCRIPTION.rst
statcamp-0.0.2.dist-info/METADATA
statcamp-0.0.2.dist-info/RECORD
statcamp-0.0.2.dist-info/WHEEL
statcamp-0.0.2.dist-info/metadata.json
statcamp-0.0.2.dist-info/top_level.txt
