Metadata-Version: 2.0
Name: statcamp
Version: 0.0.2
Summary: stat funcs from datacamp stat thinking
Home-page: https://github.com/shichaoji/statcamp
Author: Shichao(Richard) Ji
Author-email: jshichao@vt.edu
License: MIT
Download-URL: https://github.com/shichaoji/statcamp/archive/0.1.tar.gz
Keywords: data science,data mining,text mining,statistics
Platform: UNKNOWN
Classifier: License :: OSI Approved :: MIT License
Classifier: Programming Language :: Python :: 2
Requires-Dist: numpy
